im_wechat_adapter/__init__.py
im_wechat_adapter/adapter.py
im_wechat_adapter/assets/wechat.png
im_wechat_adapter/example/roleplayWithWechat.yaml
im_wechatpadpro_adapter/__init__.py
im_wechatpadpro_adapter/adapter.py
im_wechatpadpro_adapter/assets/wechat.png
im_wechatpadpro_adapter/example/roleplayWithWechat.yaml
im_wechatpadpro_adapter-0.3.1.dist-info/LICENSE
im_wechatpadpro_adapter-0.3.1.dist-info/METADATA
im_wechatpadpro_adapter-0.3.1.dist-info/WHEEL
im_wechatpadpro_adapter-0.3.1.dist-info/entry_points.txt
im_wechatpadpro_adapter-0.3.1.dist-info/top_level.txt
im_wechatpadpro_adapter-0.3.1.dist-info/RECORD
