Metadata-Version: 2.1
Name: im-wechatpadpro-adapter
Version: 0.3.1
Summary: im_wechatpadpro_adapter  for lss233/kirara-ai
Home-page: https://github.com/chuanSir123/kirara-ai-wechat
Author: chuanSir
Author-email: 416448943@qq.com
Project-URL: Bug Tracker, https://github.com/chuanSir123/kirara-ai-wechat/issues
Project-URL: Documentation, https://github.com/chuanSir123/kirara-ai-wechat/wiki
Project-URL: Source Code, https://github.com/chuanSir123/kirara-ai-wechat
Classifier: Programming Language :: Python :: 3
Classifier: License :: OSI Approved :: GNU Affero General Public License v3
Classifier: Operating System :: OS Independent
Requires-Python: >=3.8
License-File: LICENSE
Requires-Dist: kirara-ai>=3.2.0
Requires-Dist: pydantic
Requires-Dist: moviepy
